inkebase/__init__.py
inkebase/alert.py
inkebase/cat_helper.py
inkebase/child.py
inkebase/log.py
inkebase/opt.py
inkebase/proc_pool.py
inkebase/result_info.py
inkebase/service_config.py
inkebase/singleton.py
inkebase/test.py
inkebase/timer.py
inkebase/util.py
inkebase/unittests/__init__.py
inkebase/unittests/run_test.py
inkebase/unittests/test_opt.py
inkebase-1.6.0.dist-info/LICENSE
inkebase-1.6.0.dist-info/METADATA
inkebase-1.6.0.dist-info/WHEEL
inkebase-1.6.0.dist-info/top_level.txt
inkebase-1.6.0.dist-info/RECORD
