Metadata-Version: 2.1
Name: inkebase
Version: 1.6.0
Summary: Common tools
Home-page: UNKNOWN
Author: inke-bigdata
Author-email: majiankun@inke.cn
License: UNKNOWN
Platform: UNKNOWN
Classifier: Programming Language :: Python :: 2
Classifier: License :: OSI Approved :: MIT License
Classifier: Operating System :: OS Independent
